rational_functions/__init__.py
rational_functions/decomp.py
rational_functions/integral.py
rational_functions/lcm.py
rational_functions/ratfunc.py
rational_functions/roots.py
rational_functions/terms.py
rational_functions/utils.py
rational_functions-0.1.1.dist-info/METADATA
rational_functions-0.1.1.dist-info/WHEEL
rational_functions-0.1.1.dist-info/licenses/LICENSE
rational_functions-0.1.1.dist-info/RECORD
