Metadata-Version: 2.4
Name: rational-functions
Version: 0.1.1
Summary: A Python library for working with rational functions.
Project-URL: GitHub, https://github.com/stur86/rational-functions
Project-URL: Documentation, https://stur86.github.io/rational-functions/
License-File: LICENSE
Keywords: algebra,mathematics,numpy,polynomials,python library,rational functions
Classifier: Development Status :: 4 - Beta
Classifier: Intended Audience :: Developers
Classifier: Intended Audience :: Science/Research
Classifier: License :: OSI Approved :: MIT License
Classifier: Natural Language :: English
Classifier: Operating System :: OS Independent
Classifier: Programming Language :: Python :: 3
Classifier: Programming Language :: Python :: 3.10
Classifier: Programming Language :: Python :: 3.11
Classifier: Programming Language :: Python :: 3.12
Classifier: Topic :: Scientific/Engineering :: Information Analysis
Classifier: Topic :: Scientific/Engineering :: Mathematics
Requires-Python: >=3.10
Requires-Dist: numpy>=2.2.4
